{
    "id": "tpl_69e6cbddc610c3.93383478",
    "name": "Addenda_LGM",
    "location": "ADDENDA",
    "structure": {
        "root": {
            "name": null,
            "prefix": null,
            "namespace": null,
            "children": [
                {
                    "type": "field",
                    "name": "Folio",
                    "representation": "node",
                    "source": "cfdi.folio"
                },
                {
                    "type": "field",
                    "name": "Folio",
                    "representation": "node",
                    "source": "cfdi.folio"
                }
            ]
        }
    },
    "createdAt": null
}